lib4gd/__init__.py
lib4gd/resource_manager.py
lib4gd/file_transfer/__init__.py
lib4gd/file_transfer/google_drive.py
lib4gd/file_transfer/sftp.py
lib4gd/image_handling/__init__.py
lib4gd/image_handling/handle_base64.py
lib4gd/mongo_handler/__init__.py
lib4gd/mongo_handler/mongo_crud.py
lib4gd-0.2.9.dist-info/LICENSE
lib4gd-0.2.9.dist-info/METADATA
lib4gd-0.2.9.dist-info/WHEEL
lib4gd-0.2.9.dist-info/top_level.txt
lib4gd-0.2.9.dist-info/RECORD
