Metadata-Version: 2.1
Name: lib4gd
Version: 0.2.9
Summary: A comprehensive library for image handling, MongoDB, and Google Drive file management.
Home-page: https://github.com/4dg-ai/lib4gd
Author: Tejas R Simha
Author-email: tejas@4gd.ai
License: MIT
Classifier: Programming Language :: Python :: 3
Classifier: License :: OSI Approved :: MIT License
Classifier: Operating System :: OS Independent
Requires-Python: >=3.7
License-File: LICENSE
Requires-Dist: aiofiles>=0.8.0
Requires-Dist: google-auth>=2.0.0
Requires-Dist: google-auth-oauthlib>=0.4.0
Requires-Dist: google-auth-httplib2>=0.1.0
Requires-Dist: google-api-python-client>=2.0.0
Requires-Dist: numpy>=1.19.0
Requires-Dist: opencv-python>=4.5.0
Requires-Dist: Pillow>=8.0.0
Requires-Dist: asyncssh>=2.0.0
Requires-Dist: motor>=2.0.0
Requires-Dist: psutil>=5.9.0
